Metadata-Version: 2.1
Name: PyTgSend
Version: 1.2
Summary: Lightweight function to send telegram messages
Home-page: https://github.com/aptac01/PyTgSend.git
Author: Alex Tamilin
Author-email: popovalex402@gmail.com
License: MIT
Keywords: telegram tg
Platform: UNKNOWN
